flask_bs4/__init__.py
flask_bs4/forms.py
flask_bs4/internals.py
flask_bs4/nav.py
flask_bs4/utils.py
flask_bs4/static/popper.js
flask_bs4/static/popper.js.map
flask_bs4/static/popper.min.js
flask_bs4/static/popper.min.js.map
flask_bs4/static/css/bootstrap-grid.css
flask_bs4/static/css/bootstrap-grid.css.map
flask_bs4/static/css/bootstrap-grid.min.css
flask_bs4/static/css/bootstrap-grid.min.css.map
flask_bs4/static/css/bootstrap-grid.rtl.css
flask_bs4/static/css/bootstrap-grid.rtl.css.map
flask_bs4/static/css/bootstrap-grid.rtl.min.css
flask_bs4/static/css/bootstrap-grid.rtl.min.css.map
flask_bs4/static/css/bootstrap-reboot.css
flask_bs4/static/css/bootstrap-reboot.css.map
flask_bs4/static/css/bootstrap-reboot.min.css
flask_bs4/static/css/bootstrap-reboot.min.css.map
flask_bs4/static/css/bootstrap-reboot.rtl.css
flask_bs4/static/css/bootstrap-reboot.rtl.css.map
flask_bs4/static/css/bootstrap-reboot.rtl.min.css
flask_bs4/static/css/bootstrap-reboot.rtl.min.css.map
flask_bs4/static/css/bootstrap-utilities.css
flask_bs4/static/css/bootstrap-utilities.css.map
flask_bs4/static/css/bootstrap-utilities.min.css
flask_bs4/static/css/bootstrap-utilities.min.css.map
flask_bs4/static/css/bootstrap-utilities.rtl.css
flask_bs4/static/css/bootstrap-utilities.rtl.css.map
flask_bs4/static/css/bootstrap-utilities.rtl.min.css
flask_bs4/static/css/bootstrap-utilities.rtl.min.css.map
flask_bs4/static/css/bootstrap.css
flask_bs4/static/css/bootstrap.css.map
flask_bs4/static/css/bootstrap.min.css
flask_bs4/static/css/bootstrap.min.css.map
flask_bs4/static/css/bootstrap.rtl.css
flask_bs4/static/css/bootstrap.rtl.css.map
flask_bs4/static/css/bootstrap.rtl.min.css
flask_bs4/static/css/bootstrap.rtl.min.css.map
flask_bs4/static/js/bootstrap.bundle.js
flask_bs4/static/js/bootstrap.bundle.js.map
flask_bs4/static/js/bootstrap.bundle.min.js
flask_bs4/static/js/bootstrap.bundle.min.js.map
flask_bs4/static/js/bootstrap.esm.js
flask_bs4/static/js/bootstrap.esm.js.map
Flask_BS4-5.3.1.0.dist-info/LICENSE
Flask_BS4-5.3.1.0.dist-info/METADATA
Flask_BS4-5.3.1.0.dist-info/WHEEL
Flask_BS4-5.3.1.0.dist-info/top_level.txt
Flask_BS4-5.3.1.0.dist-info/RECORD
