Metadata-Version: 2.1
Name: Flask-BS4
Version: 5.3.1.0
Summary: Include Bootstrap4 in your Flask project
Home-page: https://github.com/hfilimonescu/flask-bs4
Author: Horia Filimonescu
Author-email: horia.filimonescu+github@gmail.com
License: MIT
Platform: any
Classifier: Environment :: Web Environment
Classifier: Intended Audience :: Developers
Classifier: License :: OSI Approved :: MIT License
Classifier: Operating System :: OS Independent
Classifier: Programming Language :: Python
Classifier: Programming Language :: Python :: 3
Classifier: Topic :: Internet :: WWW/HTTP :: Dynamic Content
Classifier: Topic :: Software Development :: Libraries :: Python Modules
Classifier: Framework :: Flask
License-File: LICENSE
